cellmage/__init__.py
cellmage/ambient_mode.py
cellmage/chat_manager.py
cellmage/config.py
cellmage/conversation_manager.py
cellmage/exceptions.py
cellmage/history_manager.py
cellmage/interfaces.py
cellmage/model_mapping.py
cellmage/models.py
cellmage/py.typed
cellmage/version.py
cellmage/adapters/__init__.py
cellmage/adapters/direct_client.py
cellmage/adapters/langchain_client.py
cellmage/context_providers/__init__.py
cellmage/context_providers/ipython_context_provider.py
cellmage/integrations/__init__.py
cellmage/integrations/confluence_utils.py
cellmage/integrations/gdocs_utils.py
cellmage/integrations/github_utils.py
cellmage/integrations/gitlab_utils.py
cellmage/integrations/image_utils.py
cellmage/integrations/jira_utils.py
cellmage/integrations/webcontent_utils.py
cellmage/magic_commands/__init__.py
cellmage/magic_commands/core.py
cellmage/magic_commands/history.py
cellmage/magic_commands/persistence.py
cellmage/magic_commands/sqlite_magic.py
cellmage/magic_commands/ipython/__init__.py
cellmage/magic_commands/ipython/ambient_magic.py
cellmage/magic_commands/ipython/common.py
cellmage/magic_commands/ipython/config_magic.py
cellmage/magic_commands/ipython/llm_magic.py
cellmage/magic_commands/ipython/config_handlers/__init__.py
cellmage/magic_commands/ipython/config_handlers/adapter_config_handler.py
cellmage/magic_commands/ipython/config_handlers/base_config_handler.py
cellmage/magic_commands/ipython/config_handlers/base_dir_config_handler.py
cellmage/magic_commands/ipython/config_handlers/history_display_handler.py
cellmage/magic_commands/ipython/config_handlers/model_setup_handler.py
cellmage/magic_commands/ipython/config_handlers/override_config_handler.py
cellmage/magic_commands/ipython/config_handlers/persistence_config_handler.py
cellmage/magic_commands/ipython/config_handlers/persona_config_handler.py
cellmage/magic_commands/ipython/config_handlers/snippet_config_handler.py
cellmage/magic_commands/ipython/config_handlers/status_display_handler.py
cellmage-0.9.7.dist-info/licenses/LICENSE
cellmage-0.9.7.dist-info/METADATA
cellmage-0.9.7.dist-info/WHEEL
cellmage-0.9.7.dist-info/top_level.txt
cellmage-0.9.7.dist-info/RECORD
