Metadata-Version: 2.4
Name: Cellmage
Version: 0.9.7
Summary: IPython magic commands for seamless LLM integration in Jupyter notebooks, with persona management, context snippets, and Jira/GitLab/GitHub/Google Docs integrations
Author-email: Thiago MadPin <madpin@gmail.com>
License:                                  Apache License
Project-URL: Homepage, https://github.com/madpin/cellmage
Project-URL: Repository, https://github.com/madpin/cellmage
Project-URL: Changelog, https://github.com/madpin/cellmage/blob/main/CHANGELOG.md
Classifier: Development Status :: 3 - Alpha
Classifier: Intended Audience :: Science/Research
Classifier: Intended Audience :: Developers
Classifier: Intended Audience :: Education
Classifier: License :: OSI Approved :: MIT License
Classifier: Programming Language :: Python :: 3
Classifier: Programming Language :: Python :: 3.9
Classifier: Programming Language :: Python :: 3.10
Classifier: Programming Language :: Python :: 3.11
Classifier: Programming Language :: Python :: 3.12
Classifier: Framework :: IPython
Classifier: Framework :: Jupyter
Classifier: Topic :: Scientific/Engineering :: Artificial Intelligence
Classifier: Topic :: Software Development :: Libraries :: Python Modules
Classifier: Topic :: Education :: Computer Aided Instruction (CAI)
Classifier: Natural Language :: English
Classifier: Operating System :: OS Independent
Classifier: Environment :: Console
Requires-Python: >=3.9
License-File: LICENSE
Requires-Dist: pyyaml>=6.0
Requires-Dist: pydantic>=2.0
Requires-Dist: pydantic-settings>=2.0.0
Requires-Dist: requests>=2.25.0
Requires-Dist: ipython>=8.0
Requires-Dist: requests
Requires-Dist: PyYAML
Requires-Dist: python-dotenv
Requires-Dist: types-PyYAML
Requires-Dist: types-requests
Requires-Dist: tokencostauto
Provides-Extra: langchain
Requires-Dist: langchain==0.3.24; extra == "langchain"
Requires-Dist: langchain-core>=0.1.20; extra == "langchain"
Requires-Dist: langchain-community>=0.1.20; extra == "langchain"
Requires-Dist: langchain-openai>=0.0.8; extra == "langchain"
Provides-Extra: confluence
Requires-Dist: atlassian-python-api>=3.32.0; extra == "confluence"
Requires-Dist: python-dotenv>=1.0.0; extra == "confluence"
Provides-Extra: jira
Requires-Dist: jira>=3.5.0; extra == "jira"
Requires-Dist: python-dotenv>=1.0.0; extra == "jira"
Provides-Extra: gitlab
Requires-Dist: python-gitlab>=3.15.0; extra == "gitlab"
Requires-Dist: python-dotenv>=1.0.0; extra == "gitlab"
Requires-Dist: tiktoken>=0.5.0; extra == "gitlab"
Provides-Extra: github
Requires-Dist: PyGithub>=2.1.0; extra == "github"
Requires-Dist: python-dotenv>=1.0.0; extra == "github"
Requires-Dist: tiktoken>=0.5.0; extra == "github"
Provides-Extra: gdocs
Requires-Dist: google-api-python-client>=2.97.0; extra == "gdocs"
Requires-Dist: google-auth-httplib2>=0.1.0; extra == "gdocs"
Requires-Dist: google-auth-oauthlib>=1.1.0; extra == "gdocs"
Requires-Dist: python-dotenv>=1.0.0; extra == "gdocs"
Provides-Extra: docs
Requires-Dist: Sphinx<9.0,>=6.0; extra == "docs"
Requires-Dist: furo==2024.8.6; extra == "docs"
Requires-Dist: myst-parser>=1.0; extra == "docs"
Requires-Dist: sphinx-copybutton; extra == "docs"
Requires-Dist: sphinx-autodoc-typehints==1.23.3; extra == "docs"
Requires-Dist: packaging; extra == "docs"
Requires-Dist: pydantic>=2.0; extra == "docs"
Requires-Dist: pydantic-settings>=2.0.0; extra == "docs"
Provides-Extra: dev
Requires-Dist: ruff; extra == "dev"
Requires-Dist: mypy<2.0,>=1.0; extra == "dev"
Requires-Dist: black<25.0,>=23.0; extra == "dev"
Requires-Dist: isort<5.14,>=5.12; extra == "dev"
Requires-Dist: pre-commit>=3.5.0; extra == "dev"
Requires-Dist: pytest; extra == "dev"
Requires-Dist: pytest-sphinx; extra == "dev"
Requires-Dist: pytest-cov; extra == "dev"
Requires-Dist: twine>=1.11.0; extra == "dev"
Requires-Dist: build; extra == "dev"
Requires-Dist: setuptools; extra == "dev"
Requires-Dist: wheel; extra == "dev"
Requires-Dist: Sphinx<9.0,>=6.0; extra == "dev"
Requires-Dist: furo==2024.8.6; extra == "dev"
Requires-Dist: myst-parser>=1.0; extra == "dev"
Requires-Dist: sphinx-copybutton; extra == "dev"
Requires-Dist: sphinx-autobuild; extra == "dev"
Requires-Dist: sphinx-autodoc-typehints==1.23.3; extra == "dev"
Requires-Dist: packaging; extra == "dev"
Requires-Dist: black[jupyter]; extra == "dev"
Provides-Extra: all
Requires-Dist: cellmage[confluence,gdocs,github,gitlab,jira,langchain,webcontent]; extra == "all"
Provides-Extra: webcontent
Requires-Dist: requests>=2.25.0; extra == "webcontent"
Requires-Dist: beautifulsoup4>=4.9.0; extra == "webcontent"
Requires-Dist: markdownify>=0.11.0; extra == "webcontent"
Requires-Dist: trafilatura>=1.6.0; extra == "webcontent"
Dynamic: license-file
